onedata_lambda_utils/__init__.py
onedata_lambda_utils/logging.py
onedata_lambda_utils/py.typed
onedata_lambda_utils/stats.py
onedata_lambda_utils/streaming.py
onedata_lambda_utils/types.py
onedata_lambda_utils-0.2.0.dist-info/LICENSE.txt
onedata_lambda_utils-0.2.0.dist-info/METADATA
onedata_lambda_utils-0.2.0.dist-info/WHEEL
onedata_lambda_utils-0.2.0.dist-info/top_level.txt
onedata_lambda_utils-0.2.0.dist-info/RECORD
